topsis/__init__.py
topsis/__main__.py
topsis/topsis.py
topsis_bhaumik_102303067-1.0.0.dist-info/licenses/LICENSE
topsis_bhaumik_102303067-1.0.0.dist-info/METADATA
topsis_bhaumik_102303067-1.0.0.dist-info/WHEEL
topsis_bhaumik_102303067-1.0.0.dist-info/entry_points.txt
topsis_bhaumik_102303067-1.0.0.dist-info/top_level.txt
topsis_bhaumik_102303067-1.0.0.dist-info/RECORD
