Metadata-Version: 2.4
Name: topsis-Bhaumik-102303067
Version: 1.0.0
Summary: TOPSIS implementation for multi-criteria decision analysis
Home-page: https://github.com/Bhaumik181/TOPSIS
Author: Bhaumik Verma
License: MIT
License-File: LICENSE
Requires-Dist: pandas
Requires-Dist: numpy
Dynamic: author
Dynamic: description-content-type
Dynamic: home-page
Dynamic: license
Dynamic: license-file
Dynamic: requires-dist
Dynamic: summary
